[
  {
    "title": "vampire",
    "artist": "Olivia Rodrigo",
    "lo": 51,
    "hi": 77,
    "brightness": 72,
    "year": 2023,
    "language": "English"
  },
  {
    "title": "get him back!",
    "artist": "Olivia Rodrigo",
    "lo": 51,
    "hi": 74,
    "brightness": 68,
    "year": 2023,
    "language": "English"
  },
  {
    "title": "all-american bitch",
    "artist": "Olivia Rodrigo",
    "lo": 51,
    "hi": 73,
    "brightness": 70,
    "year": 2023,
    "language": "English"
  },
  {
    "title": "bad idea right?",
    "artist": "Olivia Rodrigo",
    "lo": 53,
    "hi": 75,
    "brightness": 71,
    "year": 2023,
    "language": "English"
  },
  {
    "title": "ballad of a homeschooled girl",
    "artist": "Olivia Rodrigo",
    "lo": 52,
    "hi": 74,
    "brightness": 69,
    "year": 2023,
    "language": "English"
  },
  {
    "title": "making the bed",
    "artist": "Olivia Rodrigo",
    "lo": 50,
    "hi": 72,
    "brightness": 66,
    "year": 2023,
    "language": "English"
  },
  {
    "title": "lacy",
    "artist": "Olivia Rodrigo",
    "lo": 52,
    "hi": 73,
    "brightness": 67,
    "year": 2023,
    "language": "English"
  },
  {
    "title": "the grudge",
    "artist": "Olivia Rodrigo",
    "lo": 51,
    "hi": 76,
    "brightness": 71,
    "year": 2023,
    "language": "English"
  },
  {
    "title": "pretty isn't pretty",
    "artist": "Olivia Rodrigo",
    "lo": 53,
    "hi": 74,
    "brightness": 68,
    "year": 2023,
    "language": "English"
  },
  {
    "title": "love is embarrassing",
    "artist": "Olivia Rodrigo",
    "lo": 52,
    "hi": 73,
    "brightness": 70,
    "year": 2023,
    "language": "English"
  },
  {
    "title": "Espresso",
    "artist": "Sabrina Carpenter",
    "lo": 55,
    "hi": 69,
    "brightness": 70,
    "year": 2024,
    "language": "English"
  },
  {
    "title": "Please Please Please",
    "artist": "Sabrina Carpenter",
    "lo": 48,
    "hi": 78,
    "brightness": 69,
    "year": 2024,
    "language": "English"
  },
  {
    "title": "Feather",
    "artist": "Sabrina Carpenter",
    "lo": 53,
    "hi": 74,
    "brightness": 71,
    "year": 2023,
    "language": "English"
  },
  {
    "title": "Nonsense",
    "artist": "Sabrina Carpenter",
    "lo": 54,
    "hi": 72,
    "brightness": 70,
    "year": 2022,
    "language": "English"
  },
  {
    "title": "Taste",
    "artist": "Sabrina Carpenter",
    "lo": 52,
    "hi": 73,
    "brightness": 68,
    "year": 2024,
    "language": "English"
  },
  {
    "title": "Bed Chem",
    "artist": "Sabrina Carpenter",
    "lo": 53,
    "hi": 71,
    "brightness": 69,
    "year": 2024,
    "language": "English"
  },
  {
    "title": "Juno",
    "artist": "Sabrina Carpenter",
    "lo": 54,
    "hi": 72,
    "brightness": 70,
    "year": 2024,
    "language": "English"
  },
  {
    "title": "Good Graces",
    "artist": "Sabrina Carpenter",
    "lo": 53,
    "hi": 73,
    "brightness": 68,
    "year": 2024,
    "language": "English"
  },
  {
    "title": "Good Luck, Babe!",
    "artist": "Chappell Roan",
    "lo": 57,
    "hi": 78,
    "brightness": 72,
    "year": 2024,
    "language": "English"
  },
  {
    "title": "Pink Pony Club",
    "artist": "Chappell Roan",
    "lo": 54,
    "hi": 75,
    "brightness": 71,
    "year": 2020,
    "language": "English"
  },
  {
    "title": "Red Wine Supernova",
    "artist": "Chappell Roan",
    "lo": 53,
    "hi": 74,
    "brightness": 70,
    "year": 2023,
    "language": "English"
  },
  {
    "title": "Hot to Go!",
    "artist": "Chappell Roan",
    "lo": 55,
    "hi": 76,
    "brightness": 73,
    "year": 2023,
    "language": "English"
  },
  {
    "title": "Casual",
    "artist": "Chappell Roan",
    "lo": 54,
    "hi": 73,
    "brightness": 68,
    "year": 2023,
    "language": "English"
  },
  {
    "title": "Femininomenon",
    "artist": "Chappell Roan",
    "lo": 53,
    "hi": 75,
    "brightness": 71,
    "year": 2023,
    "language": "English"
  },
  {
    "title": "My Kink Is Karma",
    "artist": "Chappell Roan",
    "lo": 54,
    "hi": 74,
    "brightness": 69,
    "year": 2023,
    "language": "English"
  },
  {
    "title": "greedy",
    "artist": "Tate McRae",
    "lo": 54,
    "hi": 74,
    "brightness": 72,
    "year": 2023,
    "language": "English"
  },
  {
    "title": "exes",
    "artist": "Tate McRae",
    "lo": 52,
    "hi": 73,
    "brightness": 68,
    "year": 2023,
    "language": "English"
  },
  {
    "title": "run for the hills",
    "artist": "Tate McRae",
    "lo": 53,
    "hi": 72,
    "brightness": 70,
    "year": 2023,
    "language": "English"
  },
  {
    "title": "uh oh",
    "artist": "Tate McRae",
    "lo": 52,
    "hi": 71,
    "brightness": 67,
    "year": 2023,
    "language": "English"
  },
  {
    "title": "think later",
    "artist": "Tate McRae",
    "lo": 53,
    "hi": 73,
    "brightness": 69,
    "year": 2023,
    "language": "English"
  },
  {
    "title": "grave",
    "artist": "Tate McRae",
    "lo": 52,
    "hi": 72,
    "brightness": 66,
    "year": 2023,
    "language": "English"
  },
  {
    "title": "stay done",
    "artist": "Tate McRae",
    "lo": 51,
    "hi": 71,
    "brightness": 68,
    "year": 2023,
    "language": "English"
  },
  {
    "title": "That's So True",
    "artist": "Gracie Abrams",
    "lo": 51,
    "hi": 73,
    "brightness": 67,
    "year": 2024,
    "language": "English"
  },
  {
    "title": "Close to You",
    "artist": "Gracie Abrams",
    "lo": 51,
    "hi": 71,
    "brightness": 65,
    "year": 2024,
    "language": "English"
  },
  {
    "title": "I Love You, I'm Sorry",
    "artist": "Gracie Abrams",
    "lo": 51,
    "hi": 72,
    "brightness": 66,
    "year": 2024,
    "language": "English"
  },
  {
    "title": "Risk",
    "artist": "Gracie Abrams",
    "lo": 52,
    "hi": 70,
    "brightness": 64,
    "year": 2024,
    "language": "English"
  },
  {
    "title": "us.",
    "artist": "Gracie Abrams",
    "lo": 51,
    "hi": 71,
    "brightness": 65,
    "year": 2024,
    "language": "English"
  },
  {
    "title": "Blowing Smoke",
    "artist": "Gracie Abrams",
    "lo": 52,
    "hi": 72,
    "brightness": 67,
    "year": 2024,
    "language": "English"
  },
  {
    "title": "I Knew It, I Know You",
    "artist": "Gracie Abrams",
    "lo": 51,
    "hi": 70,
    "brightness": 63,
    "year": 2024,
    "language": "English"
  },
  {
    "title": "Snow Angel",
    "artist": "Reneé Rapp",
    "lo": 52,
    "hi": 77,
    "brightness": 70,
    "year": 2023,
    "language": "English"
  },
  {
    "title": "Talk Too Much",
    "artist": "Reneé Rapp",
    "lo": 53,
    "hi": 75,
    "brightness": 71,
    "year": 2023,
    "language": "English"
  },
  {
    "title": "Not My Fault",
    "artist": "Reneé Rapp",
    "lo": 54,
    "hi": 76,
    "brightness": 72,
    "year": 2023,
    "language": "English"
  },
  {
    "title": "Pretty Girls",
    "artist": "Reneé Rapp",
    "lo": 52,
    "hi": 74,
    "brightness": 68,
    "year": 2023,
    "language": "English"
  },
  {
    "title": "Poison Poison",
    "artist": "Reneé Rapp",
    "lo": 53,
    "hi": 75,
    "brightness": 69,
    "year": 2023,
    "language": "English"
  },
  {
    "title": "LUNCH",
    "artist": "Billie Eilish",
    "lo": 51,
    "hi": 70,
    "brightness": 64,
    "year": 2024,
    "language": "English"
  },
  {
    "title": "BIRDS OF A FEATHER",
    "artist": "Billie Eilish",
    "lo": 52,
    "hi": 71,
    "brightness": 66,
    "year": 2024,
    "language": "English"
  },
  {
    "title": "WILDFLOWER",
    "artist": "Billie Eilish",
    "lo": 51,
    "hi": 69,
    "brightness": 63,
    "year": 2024,
    "language": "English"
  },
  {
    "title": "SKINNY",
    "artist": "Billie Eilish",
    "lo": 51,
    "hi": 70,
    "brightness": 62,
    "year": 2024,
    "language": "English"
  },
  {
    "title": "CHIHIRO",
    "artist": "Billie Eilish",
    "lo": 52,
    "hi": 72,
    "brightness": 65,
    "year": 2024,
    "language": "English"
  },
  {
    "title": "THE GREATEST",
    "artist": "Billie Eilish",
    "lo": 51,
    "hi": 71,
    "brightness": 64,
    "year": 2024,
    "language": "English"
  },
  {
    "title": "L'AMOUR DE MA VIE",
    "artist": "Billie Eilish",
    "lo": 52,
    "hi": 70,
    "brightness": 63,
    "year": 2024,
    "language": "English"
  },
  {
    "title": "THE DINER",
    "artist": "Billie Eilish",
    "lo": 51,
    "hi": 69,
    "brightness": 62,
    "year": 2024,
    "language": "English"
  },
  {
    "title": "Lavender Haze",
    "artist": "Taylor Swift",
    "lo": 53,
    "hi": 75,
    "brightness": 68,
    "year": 2022,
    "language": "English"
  },
  {
    "title": "Maroon",
    "artist": "Taylor Swift",
    "lo": 52,
    "hi": 74,
    "brightness": 67,
    "year": 2022,
    "language": "English"
  },
  {
    "title": "Snow On The Beach",
    "artist": "Taylor Swift",
    "lo": 53,
    "hi": 73,
    "brightness": 66,
    "year": 2022,
    "language": "English"
  },
  {
    "title": "You're On Your Own, Kid",
    "artist": "Taylor Swift",
    "lo": 54,
    "hi": 76,
    "brightness": 69,
    "year": 2022,
    "language": "English"
  },
  {
    "title": "Midnight Rain",
    "artist": "Taylor Swift",
    "lo": 51,
    "hi": 72,
    "brightness": 65,
    "year": 2022,
    "language": "English"
  },
  {
    "title": "Question...?",
    "artist": "Taylor Swift",
    "lo": 53,
    "hi": 74,
    "brightness": 70,
    "year": 2022,
    "language": "English"
  },
  {
    "title": "Vigilante Shit",
    "artist": "Taylor Swift",
    "lo": 52,
    "hi": 73,
    "brightness": 68,
    "year": 2022,
    "language": "English"
  },
  {
    "title": "Bejeweled",
    "artist": "Taylor Swift",
    "lo": 53,
    "hi": 75,
    "brightness": 71,
    "year": 2022,
    "language": "English"
  },
  {
    "title": "Labyrinth",
    "artist": "Taylor Swift",
    "lo": 52,
    "hi": 74,
    "brightness": 67,
    "year": 2022,
    "language": "English"
  },
  {
    "title": "Karma",
    "artist": "Taylor Swift",
    "lo": 53,
    "hi": 75,
    "brightness": 72,
    "year": 2022,
    "language": "English"
  },
  {
    "title": "Fortnight",
    "artist": "Taylor Swift",
    "lo": 52,
    "hi": 73,
    "brightness": 66,
    "year": 2024,
    "language": "English"
  },
  {
    "title": "I Can Do It With a Broken Heart",
    "artist": "Taylor Swift",
    "lo": 53,
    "hi": 76,
    "brightness": 70,
    "year": 2024,
    "language": "English"
  },
  {
    "title": "Down Bad",
    "artist": "Taylor Swift",
    "lo": 52,
    "hi": 74,
    "brightness": 68,
    "year": 2024,
    "language": "English"
  },
  {
    "title": "Who's Afraid of Little Old Me?",
    "artist": "Taylor Swift",
    "lo": 51,
    "hi": 77,
    "brightness": 71,
    "year": 2024,
    "language": "English"
  },
  {
    "title": "Florida!!!",
    "artist": "Taylor Swift",
    "lo": 52,
    "hi": 73,
    "brightness": 67,
    "year": 2024,
    "language": "English"
  },
  {
    "title": "Guilty as Sin?",
    "artist": "Taylor Swift",
    "lo": 53,
    "hi": 75,
    "brightness": 69,
    "year": 2024,
    "language": "English"
  },
  {
    "title": "loml",
    "artist": "Taylor Swift",
    "lo": 52,
    "hi": 74,
    "brightness": 65,
    "year": 2024,
    "language": "English"
  },
  {
    "title": "Houdini",
    "artist": "Dua Lipa",
    "lo": 51,
    "hi": 72,
    "brightness": 70,
    "year": 2023,
    "language": "English"
  },
  {
    "title": "Training Season",
    "artist": "Dua Lipa",
    "lo": 52,
    "hi": 73,
    "brightness": 71,
    "year": 2024,
    "language": "English"
  },
  {
    "title": "Illusion",
    "artist": "Dua Lipa",
    "lo": 51,
    "hi": 72,
    "brightness": 69,
    "year": 2024,
    "language": "English"
  },
  {
    "title": "End of an Era",
    "artist": "Dua Lipa",
    "lo": 51,
    "hi": 71,
    "brightness": 68,
    "year": 2024,
    "language": "English"
  },
  {
    "title": "Whatcha Doing",
    "artist": "Dua Lipa",
    "lo": 52,
    "hi": 73,
    "brightness": 70,
    "year": 2024,
    "language": "English"
  },
  {
    "title": "These Walls",
    "artist": "Dua Lipa",
    "lo": 51,
    "hi": 70,
    "brightness": 67,
    "year": 2024,
    "language": "English"
  },
  {
    "title": "Happy for You",
    "artist": "Dua Lipa",
    "lo": 51,
    "hi": 72,
    "brightness": 66,
    "year": 2024,
    "language": "English"
  },
  {
    "title": "yes, and?",
    "artist": "Ariana Grande",
    "lo": 51,
    "hi": 78,
    "brightness": 72,
    "year": 2024,
    "language": "English"
  },
  {
    "title": "we can't be friends (wait for your love)",
    "artist": "Ariana Grande",
    "lo": 52,
    "hi": 77,
    "brightness": 70,
    "year": 2024,
    "language": "English"
  },
  {
    "title": "eternal sunshine",
    "artist": "Ariana Grande",
    "lo": 53,
    "hi": 76,
    "brightness": 68,
    "year": 2024,
    "language": "English"
  },
  {
    "title": "the boy is mine",
    "artist": "Ariana Grande",
    "lo": 52,
    "hi": 77,
    "brightness": 71,
    "year": 2024,
    "language": "English"
  },
  {
    "title": "bye",
    "artist": "Ariana Grande",
    "lo": 51,
    "hi": 75,
    "brightness": 67,
    "year": 2024,
    "language": "English"
  },
  {
    "title": "imperfect for you",
    "artist": "Ariana Grande",
    "lo": 52,
    "hi": 76,
    "brightness": 69,
    "year": 2024,
    "language": "English"
  },
  {
    "title": "Saturn Returns Interlude",
    "artist": "Ariana Grande",
    "lo": 53,
    "hi": 74,
    "brightness": 66,
    "year": 2024,
    "language": "English"
  },
  {
    "title": "Kill Bill",
    "artist": "SZA",
    "lo": 47,
    "hi": 79,
    "brightness": 71,
    "year": 2022,
    "language": "English"
  },
  {
    "title": "Nobody Gets Me",
    "artist": "SZA",
    "lo": 48,
    "hi": 75,
    "brightness": 68,
    "year": 2022,
    "language": "English"
  },
  {
    "title": "Shirt",
    "artist": "SZA",
    "lo": 49,
    "hi": 76,
    "brightness": 70,
    "year": 2022,
    "language": "English"
  },
  {
    "title": "Gone Girl",
    "artist": "SZA",
    "lo": 48,
    "hi": 74,
    "brightness": 66,
    "year": 2022,
    "language": "English"
  },
  {
    "title": "Blind",
    "artist": "SZA",
    "lo": 47,
    "hi": 73,
    "brightness": 65,
    "year": 2022,
    "language": "English"
  },
  {
    "title": "Used",
    "artist": "SZA",
    "lo": 48,
    "hi": 74,
    "brightness": 67,
    "year": 2022,
    "language": "English"
  },
  {
    "title": "Smoking on my Ex Pack",
    "artist": "SZA",
    "lo": 49,
    "hi": 75,
    "brightness": 69,
    "year": 2022,
    "language": "English"
  },
  {
    "title": "Ghost in the Machine",
    "artist": "SZA",
    "lo": 48,
    "hi": 73,
    "brightness": 64,
    "year": 2022,
    "language": "English"
  },
  {
    "title": "F2F",
    "artist": "SZA",
    "lo": 49,
    "hi": 76,
    "brightness": 68,
    "year": 2022,
    "language": "English"
  },
  {
    "title": "Special",
    "artist": "SZA",
    "lo": 47,
    "hi": 74,
    "brightness": 66,
    "year": 2022,
    "language": "English"
  },
  {
    "title": "Blinding Lights",
    "artist": "The Weeknd",
    "lo": 48,
    "hi": 72,
    "brightness": 70,
    "year": 2020,
    "language": "English"
  },
  {
    "title": "Save Your Tears",
    "artist": "The Weeknd",
    "lo": 49,
    "hi": 73,
    "brightness": 71,
    "year": 2020,
    "language": "English"
  },
  {
    "title": "In Your Eyes",
    "artist": "The Weeknd",
    "lo": 48,
    "hi": 71,
    "brightness": 68,
    "year": 2020,
    "language": "English"
  },
  {
    "title": "After Hours",
    "artist": "The Weeknd",
    "lo": 47,
    "hi": 74,
    "brightness": 69,
    "year": 2020,
    "language": "English"
  },
  {
    "title": "Hardest to Love",
    "artist": "The Weeknd",
    "lo": 48,
    "hi": 72,
    "brightness": 67,
    "year": 2020,
    "language": "English"
  },
  {
    "title": "Too Late",
    "artist": "The Weeknd",
    "lo": 47,
    "hi": 73,
    "brightness": 68,
    "year": 2020,
    "language": "English"
  },
  {
    "title": "Sacrifice",
    "artist": "The Weeknd",
    "lo": 49,
    "hi": 74,
    "brightness": 72,
    "year": 2022,
    "language": "English"
  },
  {
    "title": "Out of Time",
    "artist": "The Weeknd",
    "lo": 48,
    "hi": 72,
    "brightness": 69,
    "year": 2022,
    "language": "English"
  },
  {
    "title": "Is There Someone Else?",
    "artist": "The Weeknd",
    "lo": 47,
    "hi": 71,
    "brightness": 66,
    "year": 2022,
    "language": "English"
  },
  {
    "title": "Less Than Zero",
    "artist": "The Weeknd",
    "lo": 48,
    "hi": 73,
    "brightness": 68,
    "year": 2022,
    "language": "English"
  },
  {
    "title": "As It Was",
    "artist": "Harry Styles",
    "lo": 45,
    "hi": 71,
    "brightness": 68,
    "year": 2022,
    "language": "English"
  },
  {
    "title": "Late Night Talking",
    "artist": "Harry Styles",
    "lo": 46,
    "hi": 72,
    "brightness": 70,
    "year": 2022,
    "language": "English"
  },
  {
    "title": "Music for a Sushi Restaurant",
    "artist": "Harry Styles",
    "lo": 45,
    "hi": 73,
    "brightness": 71,
    "year": 2022,
    "language": "English"
  },
  {
    "title": "Matilda",
    "artist": "Harry Styles",
    "lo": 47,
    "hi": 86,
    "brightness": 72,
    "year": 2022,
    "language": "English"
  },
  {
    "title": "Satellite",
    "artist": "Harry Styles",
    "lo": 46,
    "hi": 74,
    "brightness": 69,
    "year": 2022,
    "language": "English"
  },
  {
    "title": "Grapejuice",
    "artist": "Harry Styles",
    "lo": 45,
    "hi": 72,
    "brightness": 67,
    "year": 2022,
    "language": "English"
  },
  {
    "title": "Keep Driving",
    "artist": "Harry Styles",
    "lo": 46,
    "hi": 71,
    "brightness": 66,
    "year": 2022,
    "language": "English"
  },
  {
    "title": "Boyfriends",
    "artist": "Harry Styles",
    "lo": 45,
    "hi": 70,
    "brightness": 65,
    "year": 2022,
    "language": "English"
  },
  {
    "title": "Tití Me Preguntó",
    "artist": "Bad Bunny",
    "lo": 48,
    "hi": 69,
    "brightness": 68,
    "year": 2022,
    "language": "Spanish"
  },
  {
    "title": "Moscow Mule",
    "artist": "Bad Bunny",
    "lo": 47,
    "hi": 68,
    "brightness": 66,
    "year": 2022,
    "language": "Spanish"
  },
  {
    "title": "Me Porto Bonito",
    "artist": "Bad Bunny",
    "lo": 48,
    "hi": 70,
    "brightness": 69,
    "year": 2022,
    "language": "Spanish"
  },
  {
    "title": "Yo No Soy Celoso",
    "artist": "Bad Bunny",
    "lo": 47,
    "hi": 69,
    "brightness": 67,
    "year": 2022,
    "language": "Spanish"
  },
  {
    "title": "Tarot",
    "artist": "Bad Bunny",
    "lo": 48,
    "hi": 68,
    "brightness": 65,
    "year": 2022,
    "language": "Spanish"
  },
  {
    "title": "Neverita",
    "artist": "Bad Bunny",
    "lo": 47,
    "hi": 69,
    "brightness": 68,
    "year": 2022,
    "language": "Spanish"
  },
  {
    "title": "Party",
    "artist": "Bad Bunny",
    "lo": 48,
    "hi": 70,
    "brightness": 70,
    "year": 2022,
    "language": "Spanish"
  },
  {
    "title": "Ojitos Lindos",
    "artist": "Bad Bunny",
    "lo": 47,
    "hi": 68,
    "brightness": 66,
    "year": 2022,
    "language": "Spanish"
  },
  {
    "title": "Circles",
    "artist": "Post Malone",
    "lo": 40,
    "hi": 68,
    "brightness": 66,
    "year": 2020,
    "language": "English"
  },
  {
    "title": "Sunflower",
    "artist": "Post Malone",
    "lo": 42,
    "hi": 70,
    "brightness": 70,
    "year": 2020,
    "language": "English"
  },
  {
    "title": "Chemical",
    "artist": "Post Malone",
    "lo": 41,
    "hi": 69,
    "brightness": 67,
    "year": 2023,
    "language": "English"
  },
  {
    "title": "I Like You (A Happier Song)",
    "artist": "Post Malone",
    "lo": 42,
    "hi": 71,
    "brightness": 69,
    "year": 2022,
    "language": "English"
  },
  {
    "title": "One Right Now",
    "artist": "Post Malone",
    "lo": 41,
    "hi": 70,
    "brightness": 68,
    "year": 2021,
    "language": "English"
  },
  {
    "title": "Cooped Up",
    "artist": "Post Malone",
    "lo": 42,
    "hi": 69,
    "brightness": 67,
    "year": 2022,
    "language": "English"
  },
  {
    "title": "Levitating",
    "artist": "Dua Lipa",
    "lo": 51,
    "hi": 75,
    "brightness": 73,
    "year": 2020,
    "language": "English"
  },
  {
    "title": "Don't Start Now",
    "artist": "Dua Lipa",
    "lo": 52,
    "hi": 74,
    "brightness": 72,
    "year": 2020,
    "language": "English"
  },
  {
    "title": "Physical",
    "artist": "Dua Lipa",
    "lo": 51,
    "hi": 73,
    "brightness": 71,
    "year": 2020,
    "language": "English"
  },
  {
    "title": "Break My Heart",
    "artist": "Dua Lipa",
    "lo": 52,
    "hi": 74,
    "brightness": 70,
    "year": 2020,
    "language": "English"
  },
  {
    "title": "Peaches",
    "artist": "Justin Bieber",
    "lo": 48,
    "hi": 70,
    "brightness": 68,
    "year": 2021,
    "language": "English"
  },
  {
    "title": "Stay",
    "artist": "Justin Bieber",
    "lo": 49,
    "hi": 72,
    "brightness": 71,
    "year": 2021,
    "language": "English"
  },
  {
    "title": "Ghost",
    "artist": "Justin Bieber",
    "lo": 48,
    "hi": 71,
    "brightness": 67,
    "year": 2021,
    "language": "English"
  },
  {
    "title": "positions",
    "artist": "Ariana Grande",
    "lo": 52,
    "hi": 77,
    "brightness": 70,
    "year": 2020,
    "language": "English"
  },
  {
    "title": "34+35",
    "artist": "Ariana Grande",
    "lo": 53,
    "hi": 78,
    "brightness": 72,
    "year": 2020,
    "language": "English"
  },
  {
    "title": "pov",
    "artist": "Ariana Grande",
    "lo": 51,
    "hi": 76,
    "brightness": 68,
    "year": 2020,
    "language": "English"
  },
  {
    "title": "drivers license",
    "artist": "Olivia Rodrigo",
    "lo": 50,
    "hi": 77,
    "brightness": 70,
    "year": 2021,
    "language": "English"
  },
  {
    "title": "deja vu",
    "artist": "Olivia Rodrigo",
    "lo": 52,
    "hi": 75,
    "brightness": 69,
    "year": 2021,
    "language": "English"
  },
  {
    "title": "traitor",
    "artist": "Olivia Rodrigo",
    "lo": 51,
    "hi": 74,
    "brightness": 67,
    "year": 2021,
    "language": "English"
  },
  {
    "title": "happier",
    "artist": "Olivia Rodrigo",
    "lo": 52,
    "hi": 73,
    "brightness": 66,
    "year": 2021,
    "language": "English"
  },
  {
    "title": "Therefore I Am",
    "artist": "Billie Eilish",
    "lo": 51,
    "hi": 69,
    "brightness": 65,
    "year": 2020,
    "language": "English"
  },
  {
    "title": "My Future",
    "artist": "Billie Eilish",
    "lo": 52,
    "hi": 71,
    "brightness": 64,
    "year": 2020,
    "language": "English"
  },
  {
    "title": "Happier Than Ever",
    "artist": "Billie Eilish",
    "lo": 51,
    "hi": 73,
    "brightness": 68,
    "year": 2021,
    "language": "English"
  },
  {
    "title": "Getting Older",
    "artist": "Billie Eilish",
    "lo": 52,
    "hi": 70,
    "brightness": 63,
    "year": 2021,
    "language": "English"
  },
  {
    "title": "Watermelon Sugar",
    "artist": "Harry Styles",
    "lo": 46,
    "hi": 73,
    "brightness": 72,
    "year": 2020,
    "language": "English"
  },
  {
    "title": "Adore You",
    "artist": "Harry Styles",
    "lo": 45,
    "hi": 72,
    "brightness": 70,
    "year": 2020,
    "language": "English"
  },
  {
    "title": "Golden",
    "artist": "Harry Styles",
    "lo": 46,
    "hi": 74,
    "brightness": 71,
    "year": 2020,
    "language": "English"
  },
  {
    "title": "Cardigan",
    "artist": "Taylor Swift",
    "lo": 52,
    "hi": 73,
    "brightness": 65,
    "year": 2020,
    "language": "English"
  },
  {
    "title": "Willow",
    "artist": "Taylor Swift",
    "lo": 53,
    "hi": 74,
    "brightness": 67,
    "year": 2020,
    "language": "English"
  },
  {
    "title": "champagne problems",
    "artist": "Taylor Swift",
    "lo": 52,
    "hi": 73,
    "brightness": 64,
    "year": 2020,
    "language": "English"
  },
  {
    "title": "Good Days",
    "artist": "SZA",
    "lo": 48,
    "hi": 76,
    "brightness": 69,
    "year": 2021,
    "language": "English"
  },
  {
    "title": "I Hate U",
    "artist": "SZA",
    "lo": 47,
    "hi": 75,
    "brightness": 68,
    "year": 2021,
    "language": "English"
  },
  {
    "title": "Snooze",
    "artist": "SZA",
    "lo": 48,
    "hi": 77,
    "brightness": 70,
    "year": 2022,
    "language": "English"
  },
  {
    "title": "Heat Waves",
    "artist": "Glass Animals",
    "lo": 48,
    "hi": 70,
    "brightness": 68,
    "year": 2020,
    "language": "English"
  },
  {
    "title": "Butter",
    "artist": "BTS",
    "lo": 50,
    "hi": 72,
    "brightness": 71,
    "year": 2021,
    "language": "English"
  },
  {
    "title": "Dynamite",
    "artist": "BTS",
    "lo": 49,
    "hi": 73,
    "brightness": 72,
    "year": 2020,
    "language": "English"
  },
  {
    "title": "About Damn Time",
    "artist": "Lizzo",
    "lo": 50,
    "hi": 74,
    "brightness": 73,
    "year": 2022,
    "language": "English"
  },
  {
    "title": "As It Should Be",
    "artist": "ILLENIUM",
    "lo": 46,
    "hi": 71,
    "brightness": 67,
    "year": 2023,
    "language": "English"
  },
  {
    "title": "Paint The Town Red",
    "artist": "Doja Cat",
    "lo": 50,
    "hi": 73,
    "brightness": 71,
    "year": 2023,
    "language": "English"
  },
  {
    "title": "Agora Hills",
    "artist": "Doja Cat",
    "lo": 51,
    "hi": 72,
    "brightness": 69,
    "year": 2023,
    "language": "English"
  },
  {
    "title": "Woman",
    "artist": "Doja Cat",
    "lo": 50,
    "hi": 74,
    "brightness": 70,
    "year": 2021,
    "language": "English"
  },
  {
    "title": "Need to Know",
    "artist": "Doja Cat",
    "lo": 51,
    "hi": 73,
    "brightness": 71,
    "year": 2021,
    "language": "English"
  },
  {
    "title": "You Right",
    "artist": "Doja Cat",
    "lo": 50,
    "hi": 72,
    "brightness": 68,
    "year": 2021,
    "language": "English"
  },
  {
    "title": "Yummy",
    "artist": "Justin Bieber",
    "lo": 48,
    "hi": 71,
    "brightness": 69,
    "year": 2020,
    "language": "English"
  },
  {
    "title": "Intentions",
    "artist": "Justin Bieber",
    "lo": 47,
    "hi": 70,
    "brightness": 68,
    "year": 2020,
    "language": "English"
  },
  {
    "title": "Stuck with U",
    "artist": "Ariana Grande",
    "lo": 52,
    "hi": 77,
    "brightness": 68,
    "year": 2020,
    "language": "English"
  },
  {
    "title": "Rain On Me",
    "artist": "Lady Gaga",
    "lo": 54,
    "hi": 76,
    "brightness": 73,
    "year": 2020,
    "language": "English"
  },
  {
    "title": "Die With A Smile",
    "artist": "Lady Gaga",
    "lo": 53,
    "hi": 77,
    "brightness": 70,
    "year": 2024,
    "language": "English"
  },
  {
    "title": "New Rules",
    "artist": "Dua Lipa",
    "lo": 51,
    "hi": 73,
    "brightness": 70,
    "year": 2020,
    "language": "English"
  },
  {
    "title": "Anti-Hero",
    "artist": "Taylor Swift",
    "lo": 53,
    "hi": 75,
    "brightness": 69,
    "year": 2022,
    "language": "English"
  },
  {
    "title": "Flowers",
    "artist": "Miley Cyrus",
    "lo": 52,
    "hi": 74,
    "brightness": 71,
    "year": 2023,
    "language": "English"
  },
  {
    "title": "Used to Be Young",
    "artist": "Miley Cyrus",
    "lo": 51,
    "hi": 73,
    "brightness": 68,
    "year": 2023,
    "language": "English"
  },
  {
    "title": "Jaded",
    "artist": "Miley Cyrus",
    "lo": 52,
    "hi": 72,
    "brightness": 67,
    "year": 2023,
    "language": "English"
  },
  {
    "title": "Cruel Summer",
    "artist": "Taylor Swift",
    "lo": 54,
    "hi": 76,
    "brightness": 72,
    "year": 2020,
    "language": "English"
  },
  {
    "title": "Easy On Me",
    "artist": "Adele",
    "lo": 49,
    "hi": 73,
    "brightness": 68,
    "year": 2021,
    "language": "English"
  },
  {
    "title": "Oh My God",
    "artist": "Adele",
    "lo": 50,
    "hi": 74,
    "brightness": 70,
    "year": 2021,
    "language": "English"
  },
  {
    "title": "I Drink Wine",
    "artist": "Adele",
    "lo": 49,
    "hi": 72,
    "brightness": 66,
    "year": 2021,
    "language": "English"
  },
  {
    "title": "Unholy",
    "artist": "Sam Smith",
    "lo": 47,
    "hi": 71,
    "brightness": 69,
    "year": 2022,
    "language": "English"
  },
  {
    "title": "I'm Not the Only One",
    "artist": "Sam Smith",
    "lo": 46,
    "hi": 70,
    "brightness": 65,
    "year": 2020,
    "language": "English"
  }
]
