[
  {
    "title": "Respect",
    "artist": "Aretha Franklin",
    "lo": 60,
    "hi": 79,
    "brightness": 75,
    "year": 1967,
    "language": "English"
  },
  {
    "title": "Amazing Grace",
    "artist": "Aretha Franklin",
    "lo": 53,
    "hi": 74,
    "brightness": 55,
    "year": 1972,
    "language": "English"
  },
  {
    "title": "I Say a Little Prayer",
    "artist": "Aretha Franklin",
    "lo": 58,
    "hi": 77,
    "brightness": 70,
    "year": 1968,
    "language": "English"
  },
  {
    "title": "Think",
    "artist": "Aretha Franklin",
    "lo": 57,
    "hi": 76,
    "brightness": 80,
    "year": 1968,
    "language": "English"
  },
  {
    "title": "Chain of Fools",
    "artist": "Aretha Franklin",
    "lo": 55,
    "hi": 74,
    "brightness": 72,
    "year": 1967,
    "language": "English"
  },
  {
    "title": "Bridge Over Troubled Water",
    "artist": "Aretha Franklin",
    "lo": 56,
    "hi": 79,
    "brightness": 60,
    "year": 1971,
    "language": "English"
  },
  {
    "title": "Spanish Harlem",
    "artist": "Aretha Franklin",
    "lo": 57,
    "hi": 76,
    "brightness": 68,
    "year": 1971,
    "language": "English"
  },
  {
    "title": "Day Dreaming",
    "artist": "Aretha Franklin",
    "lo": 58,
    "hi": 74,
    "brightness": 65,
    "year": 1972,
    "language": "English"
  },
  {
    "title": "Rock Steady",
    "artist": "Aretha Franklin",
    "lo": 56,
    "hi": 75,
    "brightness": 78,
    "year": 1971,
    "language": "English"
  },
  {
    "title": "Move On Up a Little Higher",
    "artist": "Mahalia Jackson",
    "lo": 56,
    "hi": 74,
    "brightness": 50,
    "year": 1947,
    "language": "English"
  },
  {
    "title": "How I Got Over",
    "artist": "Mahalia Jackson",
    "lo": 55,
    "hi": 72,
    "brightness": 48,
    "year": 1951,
    "language": "English"
  },
  {
    "title": "Take My Hand, Precious Lord",
    "artist": "Mahalia Jackson",
    "lo": 53,
    "hi": 71,
    "brightness": 45,
    "year": 1956,
    "language": "English"
  },
  {
    "title": "His Eye Is on the Sparrow",
    "artist": "Mahalia Jackson",
    "lo": 55,
    "hi": 73,
    "brightness": 52,
    "year": 1959,
    "language": "English"
  },
  {
    "title": "Didn't It Rain",
    "artist": "Mahalia Jackson",
    "lo": 56,
    "hi": 75,
    "brightness": 55,
    "year": 1958,
    "language": "English"
  },
  {
    "title": "I Believe",
    "artist": "Mahalia Jackson",
    "lo": 54,
    "hi": 72,
    "brightness": 50,
    "year": 1958,
    "language": "English"
  },
  {
    "title": "Silent Night",
    "artist": "Mahalia Jackson",
    "lo": 52,
    "hi": 70,
    "brightness": 40,
    "year": 1962,
    "language": "English"
  },
  {
    "title": "In the Upper Room",
    "artist": "Mahalia Jackson",
    "lo": 55,
    "hi": 73,
    "brightness": 48,
    "year": 1952,
    "language": "English"
  },
  {
    "title": "A Change Is Gonna Come",
    "artist": "Sam Cooke",
    "lo": 50,
    "hi": 72,
    "brightness": 58,
    "year": 1964,
    "language": "English"
  },
  {
    "title": "You Send Me",
    "artist": "Sam Cooke",
    "lo": 53,
    "hi": 70,
    "brightness": 70,
    "year": 1957,
    "language": "English"
  },
  {
    "title": "Cupid",
    "artist": "Sam Cooke",
    "lo": 55,
    "hi": 71,
    "brightness": 72,
    "year": 1961,
    "language": "English"
  },
  {
    "title": "Wonderful World",
    "artist": "Sam Cooke",
    "lo": 54,
    "hi": 69,
    "brightness": 75,
    "year": 1960,
    "language": "English"
  },
  {
    "title": "Bring It On Home to Me",
    "artist": "Sam Cooke",
    "lo": 52,
    "hi": 70,
    "brightness": 68,
    "year": 1962,
    "language": "English"
  },
  {
    "title": "Chain Gang",
    "artist": "Sam Cooke",
    "lo": 53,
    "hi": 68,
    "brightness": 65,
    "year": 1960,
    "language": "English"
  },
  {
    "title": "Touch the Hem of His Garment",
    "artist": "Sam Cooke",
    "lo": 50,
    "hi": 69,
    "brightness": 55,
    "year": 1956,
    "language": "English"
  },
  {
    "title": "Let's Stay Together",
    "artist": "Al Green",
    "lo": 52,
    "hi": 74,
    "brightness": 65,
    "year": 1971,
    "language": "English"
  },
  {
    "title": "Take Me to the River",
    "artist": "Al Green",
    "lo": 51,
    "hi": 72,
    "brightness": 70,
    "year": 1974,
    "language": "English"
  },
  {
    "title": "Tired of Being Alone",
    "artist": "Al Green",
    "lo": 53,
    "hi": 71,
    "brightness": 68,
    "year": 1971,
    "language": "English"
  },
  {
    "title": "Love and Happiness",
    "artist": "Al Green",
    "lo": 50,
    "hi": 70,
    "brightness": 72,
    "year": 1972,
    "language": "English"
  },
  {
    "title": "How Can You Mend a Broken Heart",
    "artist": "Al Green",
    "lo": 52,
    "hi": 73,
    "brightness": 60,
    "year": 1972,
    "language": "English"
  },
  {
    "title": "I'm Still in Love with You",
    "artist": "Al Green",
    "lo": 51,
    "hi": 71,
    "brightness": 67,
    "year": 1972,
    "language": "English"
  },
  {
    "title": "Precious Lord",
    "artist": "Al Green",
    "lo": 50,
    "hi": 70,
    "brightness": 52,
    "year": 1982,
    "language": "English"
  },
  {
    "title": "Everything's Gonna Be Alright",
    "artist": "Al Green",
    "lo": 52,
    "hi": 72,
    "brightness": 58,
    "year": 1987,
    "language": "English"
  },
  {
    "title": "Stomp",
    "artist": "Kirk Franklin",
    "lo": 48,
    "hi": 67,
    "brightness": 85,
    "year": 1997,
    "language": "English"
  },
  {
    "title": "Revolution",
    "artist": "Kirk Franklin",
    "lo": 49,
    "hi": 68,
    "brightness": 80,
    "year": 1998,
    "language": "English"
  },
  {
    "title": "Lean on Me",
    "artist": "Kirk Franklin",
    "lo": 50,
    "hi": 69,
    "brightness": 75,
    "year": 1998,
    "language": "English"
  },
  {
    "title": "Imagine Me",
    "artist": "Kirk Franklin",
    "lo": 51,
    "hi": 70,
    "brightness": 70,
    "year": 2005,
    "language": "English"
  },
  {
    "title": "I Smile",
    "artist": "Kirk Franklin",
    "lo": 50,
    "hi": 68,
    "brightness": 78,
    "year": 2011,
    "language": "English"
  },
  {
    "title": "My Life Is in Your Hands",
    "artist": "Kirk Franklin",
    "lo": 48,
    "hi": 67,
    "brightness": 65,
    "year": 1996,
    "language": "English"
  },
  {
    "title": "Brighter Day",
    "artist": "Kirk Franklin",
    "lo": 49,
    "hi": 68,
    "brightness": 82,
    "year": 1996,
    "language": "English"
  },
  {
    "title": "Silver and Gold",
    "artist": "Kirk Franklin",
    "lo": 50,
    "hi": 69,
    "brightness": 72,
    "year": 1993,
    "language": "English"
  },
  {
    "title": "Stand",
    "artist": "Donnie McClurkin",
    "lo": 48,
    "hi": 70,
    "brightness": 68,
    "year": 1996,
    "language": "English"
  },
  {
    "title": "We Fall Down",
    "artist": "Donnie McClurkin",
    "lo": 50,
    "hi": 69,
    "brightness": 60,
    "year": 1998,
    "language": "English"
  },
  {
    "title": "Great Is Your Mercy",
    "artist": "Donnie McClurkin",
    "lo": 49,
    "hi": 68,
    "brightness": 65,
    "year": 2000,
    "language": "English"
  },
  {
    "title": "Holy",
    "artist": "Donnie McClurkin",
    "lo": 51,
    "hi": 71,
    "brightness": 58,
    "year": 2003,
    "language": "English"
  },
  {
    "title": "Speak to My Heart",
    "artist": "Donnie McClurkin",
    "lo": 48,
    "hi": 67,
    "brightness": 62,
    "year": 1996,
    "language": "English"
  },
  {
    "title": "Oh Happy Day",
    "artist": "Edwin Hawkins Singers",
    "lo": 55,
    "hi": 76,
    "brightness": 80,
    "year": 1969,
    "language": "English"
  },
  {
    "title": "Total Praise",
    "artist": "Richard Smallwood",
    "lo": 52,
    "hi": 74,
    "brightness": 62,
    "year": 1996,
    "language": "English"
  },
  {
    "title": "Center of My Joy",
    "artist": "Richard Smallwood",
    "lo": 53,
    "hi": 73,
    "brightness": 68,
    "year": 1987,
    "language": "English"
  },
  {
    "title": "I Love the Lord",
    "artist": "Whitney Houston",
    "lo": 58,
    "hi": 79,
    "brightness": 70,
    "year": 1996,
    "language": "English"
  },
  {
    "title": "His Eye Is on the Sparrow",
    "artist": "Whitney Houston",
    "lo": 56,
    "hi": 77,
    "brightness": 65,
    "year": 1996,
    "language": "English"
  },
  {
    "title": "Go Higher",
    "artist": "Yolanda Adams",
    "lo": 57,
    "hi": 78,
    "brightness": 75,
    "year": 2003,
    "language": "English"
  },
  {
    "title": "Open My Heart",
    "artist": "Yolanda Adams",
    "lo": 56,
    "hi": 77,
    "brightness": 70,
    "year": 1999,
    "language": "English"
  },
  {
    "title": "The Battle Is the Lord's",
    "artist": "Yolanda Adams",
    "lo": 55,
    "hi": 76,
    "brightness": 72,
    "year": 1998,
    "language": "English"
  },
  {
    "title": "Victory",
    "artist": "Yolanda Adams",
    "lo": 57,
    "hi": 77,
    "brightness": 78,
    "year": 2005,
    "language": "English"
  },
  {
    "title": "Through the Storm",
    "artist": "Yolanda Adams",
    "lo": 56,
    "hi": 75,
    "brightness": 68,
    "year": 2001,
    "language": "English"
  },
  {
    "title": "The Only Way",
    "artist": "Yolanda Adams",
    "lo": 55,
    "hi": 76,
    "brightness": 65,
    "year": 1995,
    "language": "English"
  },
  {
    "title": "Alabaster Box",
    "artist": "CeCe Winans",
    "lo": 56,
    "hi": 77,
    "brightness": 68,
    "year": 1999,
    "language": "English"
  },
  {
    "title": "Throne Room",
    "artist": "CeCe Winans",
    "lo": 57,
    "hi": 78,
    "brightness": 70,
    "year": 2003,
    "language": "English"
  },
  {
    "title": "Pray",
    "artist": "CeCe Winans",
    "lo": 55,
    "hi": 76,
    "brightness": 65,
    "year": 1997,
    "language": "English"
  },
  {
    "title": "Well Alright",
    "artist": "CeCe Winans",
    "lo": 56,
    "hi": 75,
    "brightness": 72,
    "year": 2000,
    "language": "English"
  },
  {
    "title": "He's Concerned",
    "artist": "CeCe Winans",
    "lo": 54,
    "hi": 74,
    "brightness": 62,
    "year": 2000,
    "language": "English"
  },
  {
    "title": "Never Lost",
    "artist": "CeCe Winans",
    "lo": 55,
    "hi": 76,
    "brightness": 68,
    "year": 2021,
    "language": "English"
  },
  {
    "title": "Tomorrow",
    "artist": "BeBe & CeCe Winans",
    "lo": 54,
    "hi": 75,
    "brightness": 70,
    "year": 1987,
    "language": "English"
  },
  {
    "title": "Addictive Love",
    "artist": "BeBe & CeCe Winans",
    "lo": 53,
    "hi": 74,
    "brightness": 75,
    "year": 1991,
    "language": "English"
  },
  {
    "title": "Lost Without You",
    "artist": "BeBe & CeCe Winans",
    "lo": 52,
    "hi": 73,
    "brightness": 68,
    "year": 1991,
    "language": "English"
  },
  {
    "title": "I'll Take You There",
    "artist": "BeBe & CeCe Winans",
    "lo": 54,
    "hi": 74,
    "brightness": 72,
    "year": 1991,
    "language": "English"
  },
  {
    "title": "My Soul Has Been Anchored",
    "artist": "The Winans",
    "lo": 50,
    "hi": 70,
    "brightness": 60,
    "year": 1984,
    "language": "English"
  },
  {
    "title": "Tomorrow",
    "artist": "The Winans",
    "lo": 51,
    "hi": 71,
    "brightness": 65,
    "year": 1984,
    "language": "English"
  },
  {
    "title": "It's Time",
    "artist": "The Winans",
    "lo": 49,
    "hi": 69,
    "brightness": 68,
    "year": 1990,
    "language": "English"
  },
  {
    "title": "A Friend",
    "artist": "The Winans",
    "lo": 50,
    "hi": 70,
    "brightness": 62,
    "year": 1987,
    "language": "English"
  },
  {
    "title": "Soon and Very Soon",
    "artist": "Andrae Crouch",
    "lo": 52,
    "hi": 71,
    "brightness": 75,
    "year": 1976,
    "language": "English"
  },
  {
    "title": "My Tribute (To God Be the Glory)",
    "artist": "Andrae Crouch",
    "lo": 51,
    "hi": 70,
    "brightness": 70,
    "year": 1971,
    "language": "English"
  },
  {
    "title": "The Blood Will Never Lose Its Power",
    "artist": "Andrae Crouch",
    "lo": 50,
    "hi": 69,
    "brightness": 65,
    "year": 1966,
    "language": "English"
  },
  {
    "title": "Through It All",
    "artist": "Andrae Crouch",
    "lo": 49,
    "hi": 68,
    "brightness": 60,
    "year": 1971,
    "language": "English"
  },
  {
    "title": "I'll Be Thinking of You",
    "artist": "Andrae Crouch",
    "lo": 51,
    "hi": 70,
    "brightness": 68,
    "year": 1979,
    "language": "English"
  },
  {
    "title": "Jesus Is the Answer",
    "artist": "Andrae Crouch",
    "lo": 50,
    "hi": 69,
    "brightness": 72,
    "year": 1973,
    "language": "English"
  },
  {
    "title": "Can't Nobody Do Me Like Jesus",
    "artist": "Andrae Crouch",
    "lo": 52,
    "hi": 70,
    "brightness": 70,
    "year": 1972,
    "language": "English"
  },
  {
    "title": "Goin' Up Yonder",
    "artist": "Walter Hawkins",
    "lo": 53,
    "hi": 73,
    "brightness": 68,
    "year": 1975,
    "language": "English"
  },
  {
    "title": "Be Grateful",
    "artist": "Walter Hawkins",
    "lo": 52,
    "hi": 72,
    "brightness": 65,
    "year": 1977,
    "language": "English"
  },
  {
    "title": "Changed",
    "artist": "Tramaine Hawkins",
    "lo": 55,
    "hi": 76,
    "brightness": 70,
    "year": 1987,
    "language": "English"
  },
  {
    "title": "Fall Down (Spirit of God)",
    "artist": "Tramaine Hawkins",
    "lo": 56,
    "hi": 77,
    "brightness": 72,
    "year": 1985,
    "language": "English"
  },
  {
    "title": "What Shall I Do",
    "artist": "Tramaine Hawkins",
    "lo": 54,
    "hi": 75,
    "brightness": 68,
    "year": 1991,
    "language": "English"
  },
  {
    "title": "Holy One",
    "artist": "Tramaine Hawkins",
    "lo": 55,
    "hi": 76,
    "brightness": 65,
    "year": 1988,
    "language": "English"
  },
  {
    "title": "People Get Ready",
    "artist": "The Impressions",
    "lo": 52,
    "hi": 70,
    "brightness": 65,
    "year": 1965,
    "language": "English"
  },
  {
    "title": "Amen",
    "artist": "The Impressions",
    "lo": 51,
    "hi": 69,
    "brightness": 70,
    "year": 1964,
    "language": "English"
  },
  {
    "title": "Keep On Pushing",
    "artist": "The Impressions",
    "lo": 53,
    "hi": 71,
    "brightness": 72,
    "year": 1964,
    "language": "English"
  },
  {
    "title": "I'm So Grateful",
    "artist": "The Impressions",
    "lo": 52,
    "hi": 70,
    "brightness": 68,
    "year": 1966,
    "language": "English"
  },
  {
    "title": "Try a Little Tenderness",
    "artist": "Otis Redding",
    "lo": 48,
    "hi": 70,
    "brightness": 75,
    "year": 1966,
    "language": "English"
  },
  {
    "title": "(Sittin' On) The Dock of the Bay",
    "artist": "Otis Redding",
    "lo": 50,
    "hi": 68,
    "brightness": 62,
    "year": 1968,
    "language": "English"
  },
  {
    "title": "I've Been Loving You Too Long",
    "artist": "Otis Redding",
    "lo": 49,
    "hi": 69,
    "brightness": 70,
    "year": 1965,
    "language": "English"
  },
  {
    "title": "These Arms of Mine",
    "artist": "Otis Redding",
    "lo": 50,
    "hi": 67,
    "brightness": 65,
    "year": 1963,
    "language": "English"
  },
  {
    "title": "Respect",
    "artist": "Otis Redding",
    "lo": 48,
    "hi": 68,
    "brightness": 72,
    "year": 1965,
    "language": "English"
  },
  {
    "title": "When a Man Loves a Woman",
    "artist": "Percy Sledge",
    "lo": 47,
    "hi": 67,
    "brightness": 68,
    "year": 1966,
    "language": "English"
  },
  {
    "title": "Warm and Tender Love",
    "artist": "Percy Sledge",
    "lo": 48,
    "hi": 66,
    "brightness": 65,
    "year": 1966,
    "language": "English"
  },
  {
    "title": "It Tears Me Up",
    "artist": "Percy Sledge",
    "lo": 49,
    "hi": 67,
    "brightness": 70,
    "year": 1966,
    "language": "English"
  },
  {
    "title": "In the Midnight Hour",
    "artist": "Wilson Pickett",
    "lo": 50,
    "hi": 70,
    "brightness": 78,
    "year": 1965,
    "language": "English"
  },
  {
    "title": "Mustang Sally",
    "artist": "Wilson Pickett",
    "lo": 51,
    "hi": 69,
    "brightness": 75,
    "year": 1966,
    "language": "English"
  },
  {
    "title": "Land of 1000 Dances",
    "artist": "Wilson Pickett",
    "lo": 52,
    "hi": 70,
    "brightness": 80,
    "year": 1966,
    "language": "English"
  },
  {
    "title": "634-5789",
    "artist": "Wilson Pickett",
    "lo": 51,
    "hi": 69,
    "brightness": 72,
    "year": 1966,
    "language": "English"
  },
  {
    "title": "Reach Out I'll Be There",
    "artist": "The Four Tops",
    "lo": 50,
    "hi": 72,
    "brightness": 75,
    "year": 1966,
    "language": "English"
  },
  {
    "title": "I Can't Help Myself",
    "artist": "The Four Tops",
    "lo": 52,
    "hi": 71,
    "brightness": 78,
    "year": 1965,
    "language": "English"
  },
  {
    "title": "Bernadette",
    "artist": "The Four Tops",
    "lo": 51,
    "hi": 73,
    "brightness": 72,
    "year": 1967,
    "language": "English"
  },
  {
    "title": "Standing in the Shadows of Love",
    "artist": "The Four Tops",
    "lo": 50,
    "hi": 71,
    "brightness": 70,
    "year": 1967,
    "language": "English"
  },
  {
    "title": "Ain't No Mountain High Enough",
    "artist": "Marvin Gaye & Tammi Terrell",
    "lo": 53,
    "hi": 74,
    "brightness": 80,
    "year": 1967,
    "language": "English"
  },
  {
    "title": "Your Precious Love",
    "artist": "Marvin Gaye & Tammi Terrell",
    "lo": 52,
    "hi": 72,
    "brightness": 75,
    "year": 1967,
    "language": "English"
  },
  {
    "title": "Ain't Nothing Like the Real Thing",
    "artist": "Marvin Gaye & Tammi Terrell",
    "lo": 51,
    "hi": 71,
    "brightness": 78,
    "year": 1968,
    "language": "English"
  },
  {
    "title": "What's Going On",
    "artist": "Marvin Gaye",
    "lo": 48,
    "hi": 69,
    "brightness": 62,
    "year": 1971,
    "language": "English"
  },
  {
    "title": "Mercy Mercy Me",
    "artist": "Marvin Gaye",
    "lo": 49,
    "hi": 68,
    "brightness": 65,
    "year": 1971,
    "language": "English"
  },
  {
    "title": "Inner City Blues",
    "artist": "Marvin Gaye",
    "lo": 47,
    "hi": 67,
    "brightness": 58,
    "year": 1971,
    "language": "English"
  },
  {
    "title": "Let's Get It On",
    "artist": "Marvin Gaye",
    "lo": 50,
    "hi": 70,
    "brightness": 70,
    "year": 1973,
    "language": "English"
  },
  {
    "title": "Sexual Healing",
    "artist": "Marvin Gaye",
    "lo": 51,
    "hi": 69,
    "brightness": 68,
    "year": 1982,
    "language": "English"
  },
  {
    "title": "I Heard It Through the Grapevine",
    "artist": "Marvin Gaye",
    "lo": 49,
    "hi": 68,
    "brightness": 72,
    "year": 1968,
    "language": "English"
  },
  {
    "title": "A Song for You",
    "artist": "Donny Hathaway",
    "lo": 47,
    "hi": 70,
    "brightness": 60,
    "year": 1971,
    "language": "English"
  },
  {
    "title": "The Ghetto",
    "artist": "Donny Hathaway",
    "lo": 48,
    "hi": 69,
    "brightness": 65,
    "year": 1970,
    "language": "English"
  },
  {
    "title": "Where Is the Love",
    "artist": "Roberta Flack & Donny Hathaway",
    "lo": 50,
    "hi": 72,
    "brightness": 68,
    "year": 1972,
    "language": "English"
  },
  {
    "title": "The Closer I Get to You",
    "artist": "Roberta Flack & Donny Hathaway",
    "lo": 51,
    "hi": 71,
    "brightness": 70,
    "year": 1978,
    "language": "English"
  },
  {
    "title": "Killing Me Softly with His Song",
    "artist": "Roberta Flack",
    "lo": 52,
    "hi": 73,
    "brightness": 65,
    "year": 1973,
    "language": "English"
  },
  {
    "title": "The First Time Ever I Saw Your Face",
    "artist": "Roberta Flack",
    "lo": 51,
    "hi": 71,
    "brightness": 58,
    "year": 1972,
    "language": "English"
  },
  {
    "title": "Feel Like Makin' Love",
    "artist": "Roberta Flack",
    "lo": 53,
    "hi": 72,
    "brightness": 68,
    "year": 1974,
    "language": "English"
  },
  {
    "title": "I'm Every Woman",
    "artist": "Chaka Khan",
    "lo": 54,
    "hi": 76,
    "brightness": 82,
    "year": 1978,
    "language": "English"
  },
  {
    "title": "Ain't Nobody",
    "artist": "Chaka Khan",
    "lo": 55,
    "hi": 77,
    "brightness": 80,
    "year": 1983,
    "language": "English"
  },
  {
    "title": "Through the Fire",
    "artist": "Chaka Khan",
    "lo": 56,
    "hi": 78,
    "brightness": 75,
    "year": 1984,
    "language": "English"
  },
  {
    "title": "Sweet Thing",
    "artist": "Chaka Khan",
    "lo": 54,
    "hi": 75,
    "brightness": 70,
    "year": 1975,
    "language": "English"
  },
  {
    "title": "Midnight Train to Georgia",
    "artist": "Gladys Knight & The Pips",
    "lo": 52,
    "hi": 72,
    "brightness": 72,
    "year": 1973,
    "language": "English"
  },
  {
    "title": "Neither One of Us",
    "artist": "Gladys Knight & The Pips",
    "lo": 53,
    "hi": 71,
    "brightness": 68,
    "year": 1973,
    "language": "English"
  },
  {
    "title": "If I Were Your Woman",
    "artist": "Gladys Knight & The Pips",
    "lo": 54,
    "hi": 73,
    "brightness": 70,
    "year": 1970,
    "language": "English"
  },
  {
    "title": "I Heard It Through the Grapevine",
    "artist": "Gladys Knight & The Pips",
    "lo": 53,
    "hi": 72,
    "brightness": 75,
    "year": 1967,
    "language": "English"
  },
  {
    "title": "Best Thing That Ever Happened to Me",
    "artist": "Gladys Knight & The Pips",
    "lo": 52,
    "hi": 71,
    "brightness": 68,
    "year": 1974,
    "language": "English"
  },
  {
    "title": "Just My Imagination",
    "artist": "The Temptations",
    "lo": 50,
    "hi": 70,
    "brightness": 70,
    "year": 1971,
    "language": "English"
  },
  {
    "title": "Papa Was a Rollin' Stone",
    "artist": "The Temptations",
    "lo": 48,
    "hi": 69,
    "brightness": 65,
    "year": 1972,
    "language": "English"
  },
  {
    "title": "My Girl",
    "artist": "The Temptations",
    "lo": 52,
    "hi": 71,
    "brightness": 78,
    "year": 1964,
    "language": "English"
  },
  {
    "title": "Ain't Too Proud to Beg",
    "artist": "The Temptations",
    "lo": 51,
    "hi": 70,
    "brightness": 75,
    "year": 1966,
    "language": "English"
  },
  {
    "title": "Ball of Confusion",
    "artist": "The Temptations",
    "lo": 50,
    "hi": 69,
    "brightness": 72,
    "year": 1970,
    "language": "English"
  },
  {
    "title": "I Wish It Would Rain",
    "artist": "The Temptations",
    "lo": 49,
    "hi": 68,
    "brightness": 68,
    "year": 1967,
    "language": "English"
  },
  {
    "title": "Stand By Me",
    "artist": "Ben E. King",
    "lo": 48,
    "hi": 68,
    "brightness": 70,
    "year": 1961,
    "language": "English"
  },
  {
    "title": "Spanish Harlem",
    "artist": "Ben E. King",
    "lo": 49,
    "hi": 67,
    "brightness": 68,
    "year": 1960,
    "language": "English"
  },
  {
    "title": "Don't Play That Song",
    "artist": "Ben E. King",
    "lo": 47,
    "hi": 66,
    "brightness": 65,
    "year": 1962,
    "language": "English"
  },
  {
    "title": "Shout",
    "artist": "The Isley Brothers",
    "lo": 52,
    "hi": 74,
    "brightness": 85,
    "year": 1959,
    "language": "English"
  },
  {
    "title": "Twist and Shout",
    "artist": "The Isley Brothers",
    "lo": 51,
    "hi": 72,
    "brightness": 82,
    "year": 1962,
    "language": "English"
  },
  {
    "title": "It's Your Thing",
    "artist": "The Isley Brothers",
    "lo": 50,
    "hi": 71,
    "brightness": 78,
    "year": 1969,
    "language": "English"
  },
  {
    "title": "That Lady",
    "artist": "The Isley Brothers",
    "lo": 51,
    "hi": 73,
    "brightness": 75,
    "year": 1973,
    "language": "English"
  },
  {
    "title": "For the Love of You",
    "artist": "The Isley Brothers",
    "lo": 49,
    "hi": 70,
    "brightness": 68,
    "year": 1975,
    "language": "English"
  },
  {
    "title": "Lean on Me",
    "artist": "Bill Withers",
    "lo": 48,
    "hi": 67,
    "brightness": 72,
    "year": 1972,
    "language": "English"
  },
  {
    "title": "Ain't No Sunshine",
    "artist": "Bill Withers",
    "lo": 47,
    "hi": 65,
    "brightness": 55,
    "year": 1971,
    "language": "English"
  },
  {
    "title": "Use Me",
    "artist": "Bill Withers",
    "lo": 49,
    "hi": 68,
    "brightness": 70,
    "year": 1972,
    "language": "English"
  },
  {
    "title": "Lovely Day",
    "artist": "Bill Withers",
    "lo": 50,
    "hi": 69,
    "brightness": 78,
    "year": 1977,
    "language": "English"
  },
  {
    "title": "Just the Two of Us",
    "artist": "Bill Withers",
    "lo": 48,
    "hi": 67,
    "brightness": 70,
    "year": 1981,
    "language": "English"
  },
  {
    "title": "I'll Take You There",
    "artist": "The Staple Singers",
    "lo": 50,
    "hi": 70,
    "brightness": 75,
    "year": 1972,
    "language": "English"
  },
  {
    "title": "Respect Yourself",
    "artist": "The Staple Singers",
    "lo": 51,
    "hi": 71,
    "brightness": 78,
    "year": 1971,
    "language": "English"
  },
  {
    "title": "Let's Do It Again",
    "artist": "The Staple Singers",
    "lo": 52,
    "hi": 72,
    "brightness": 80,
    "year": 1975,
    "language": "English"
  },
  {
    "title": "If You're Ready (Come Go with Me)",
    "artist": "The Staple Singers",
    "lo": 50,
    "hi": 70,
    "brightness": 72,
    "year": 1973,
    "language": "English"
  },
  {
    "title": "Will the Circle Be Unbroken",
    "artist": "The Staple Singers",
    "lo": 49,
    "hi": 68,
    "brightness": 60,
    "year": 1972,
    "language": "English"
  },
  {
    "title": "Wade in the Water",
    "artist": "The Staple Singers",
    "lo": 51,
    "hi": 71,
    "brightness": 65,
    "year": 1966,
    "language": "English"
  },
  {
    "title": "Just a Little Bit",
    "artist": "Rosie & The Originals",
    "lo": 54,
    "hi": 72,
    "brightness": 70,
    "year": 1960,
    "language": "English"
  },
  {
    "title": "This Little Light of Mine",
    "artist": "Odetta",
    "lo": 52,
    "hi": 71,
    "brightness": 68,
    "year": 1962,
    "language": "English"
  },
  {
    "title": "Oh Freedom",
    "artist": "Odetta",
    "lo": 51,
    "hi": 70,
    "brightness": 65,
    "year": 1960,
    "language": "English"
  },
  {
    "title": "Sometimes I Feel Like a Motherless Child",
    "artist": "Odetta",
    "lo": 50,
    "hi": 69,
    "brightness": 55,
    "year": 1960,
    "language": "English"
  },
  {
    "title": "Hold On",
    "artist": "En Vogue",
    "lo": 55,
    "hi": 76,
    "brightness": 80,
    "year": 1990,
    "language": "English"
  },
  {
    "title": "Free Your Mind",
    "artist": "En Vogue",
    "lo": 56,
    "hi": 77,
    "brightness": 82,
    "year": 1992,
    "language": "English"
  },
  {
    "title": "My Lovin' (You're Never Gonna Get It)",
    "artist": "En Vogue",
    "lo": 54,
    "hi": 75,
    "brightness": 78,
    "year": 1992,
    "language": "English"
  },
  {
    "title": "If I Had No Loot",
    "artist": "Tony! Toni! Toné!",
    "lo": 50,
    "hi": 69,
    "brightness": 75,
    "year": 1993,
    "language": "English"
  },
  {
    "title": "It Never Rains (In Southern California)",
    "artist": "Tony! Toni! Toné!",
    "lo": 51,
    "hi": 70,
    "brightness": 72,
    "year": 1990,
    "language": "English"
  },
  {
    "title": "Whatever You Want",
    "artist": "Tony! Toni! Toné!",
    "lo": 49,
    "hi": 68,
    "brightness": 70,
    "year": 1990,
    "language": "English"
  },
  {
    "title": "End of the Road",
    "artist": "Boyz II Men",
    "lo": 48,
    "hi": 70,
    "brightness": 65,
    "year": 1992,
    "language": "English"
  },
  {
    "title": "I'll Make Love to You",
    "artist": "Boyz II Men",
    "lo": 49,
    "hi": 71,
    "brightness": 68,
    "year": 1994,
    "language": "English"
  },
  {
    "title": "Motownphilly",
    "artist": "Boyz II Men",
    "lo": 50,
    "hi": 72,
    "brightness": 75,
    "year": 1991,
    "language": "English"
  },
  {
    "title": "It's So Hard to Say Goodbye to Yesterday",
    "artist": "Boyz II Men",
    "lo": 47,
    "hi": 69,
    "brightness": 58,
    "year": 1991,
    "language": "English"
  },
  {
    "title": "On Bended Knee",
    "artist": "Boyz II Men",
    "lo": 48,
    "hi": 70,
    "brightness": 62,
    "year": 1994,
    "language": "English"
  },
  {
    "title": "Water Runs Dry",
    "artist": "Boyz II Men",
    "lo": 49,
    "hi": 69,
    "brightness": 65,
    "year": 1995,
    "language": "English"
  },
  {
    "title": "Endless Love",
    "artist": "Diana Ross & Lionel Richie",
    "lo": 52,
    "hi": 74,
    "brightness": 70,
    "year": 1981,
    "language": "English"
  },
  {
    "title": "Ain't No Mountain High Enough",
    "artist": "Diana Ross",
    "lo": 55,
    "hi": 76,
    "brightness": 78,
    "year": 1970,
    "language": "English"
  },
  {
    "title": "I'm Coming Out",
    "artist": "Diana Ross",
    "lo": 54,
    "hi": 75,
    "brightness": 80,
    "year": 1980,
    "language": "English"
  },
  {
    "title": "Reach Out and Touch (Somebody's Hand)",
    "artist": "Diana Ross",
    "lo": 53,
    "hi": 74,
    "brightness": 72,
    "year": 1970,
    "language": "English"
  },
  {
    "title": "Upside Down",
    "artist": "Diana Ross",
    "lo": 54,
    "hi": 75,
    "brightness": 82,
    "year": 1980,
    "language": "English"
  },
  {
    "title": "Sir Duke",
    "artist": "Stevie Wonder",
    "lo": 52,
    "hi": 74,
    "brightness": 85,
    "year": 1976,
    "language": "English"
  },
  {
    "title": "Superstition",
    "artist": "Stevie Wonder",
    "lo": 50,
    "hi": 72,
    "brightness": 82,
    "year": 1972,
    "language": "English"
  },
  {
    "title": "Signed, Sealed, Delivered I'm Yours",
    "artist": "Stevie Wonder",
    "lo": 51,
    "hi": 73,
    "brightness": 80,
    "year": 1970,
    "language": "English"
  },
  {
    "title": "Isn't She Lovely",
    "artist": "Stevie Wonder",
    "lo": 53,
    "hi": 74,
    "brightness": 78,
    "year": 1976,
    "language": "English"
  },
  {
    "title": "Higher Ground",
    "artist": "Stevie Wonder",
    "lo": 52,
    "hi": 75,
    "brightness": 83,
    "year": 1973,
    "language": "English"
  },
  {
    "title": "Living for the City",
    "artist": "Stevie Wonder",
    "lo": 51,
    "hi": 73,
    "brightness": 75,
    "year": 1973,
    "language": "English"
  },
  {
    "title": "You Are the Sunshine of My Life",
    "artist": "Stevie Wonder",
    "lo": 53,
    "hi": 72,
    "brightness": 78,
    "year": 1972,
    "language": "English"
  },
  {
    "title": "As",
    "artist": "Stevie Wonder",
    "lo": 50,
    "hi": 71,
    "brightness": 70,
    "year": 1976,
    "language": "English"
  },
  {
    "title": "For Once in My Life",
    "artist": "Stevie Wonder",
    "lo": 54,
    "hi": 73,
    "brightness": 80,
    "year": 1968,
    "language": "English"
  }
]
